setup.cfg
setup.py
pymono/__init__.py
pymono/config.py
pymono.egg-info/PKG-INFO
pymono.egg-info/SOURCES.txt
pymono.egg-info/dependency_links.txt
pymono.egg-info/requires.txt
pymono.egg-info/top_level.txt
pymono/controllers/BoardCtrl.py
pymono/controllers/CellDetailsCtrl.py
pymono/controllers/DiceCtrl.py
pymono/controllers/PlayersCtrl.py
pymono/data/board.py
pymono/lib/cocos2d.py
pymono/lib/observable.py
pymono/lib/popup.py
pymono/lib/utils.py
pymono/models/Board.py
pymono/models/BoardLayout.py
pymono/models/Cell.py
pymono/models/Player.py
pymono/views/BoardView.py
pymono/views/CellDetailsView.py
pymono/views/DiceView.py
pymono/views/PlayersView.py