Metadata-Version: 1.0
Name: pymono
Version: 1.0.2
Summary: Monopoly game built with Python 3 & Cocos2d
Home-page: https://github.com/MrKomish/Monopoly
Author: Michael Konviser
Author-email: misha.konviser@gmail.com
License: MIT
Keywords: monopoly,game,board,pymono,mono
Platform: UNKNOWN
